arcface/ArcFace.py
arcface/__init__.py
arcface/lib/__init__.py
arcface/lib/layers.py
arcface/lib/models.py
arcface/lib/utils.py
arcface-0.0.8.dist-info/LICENSE
arcface-0.0.8.dist-info/METADATA
arcface-0.0.8.dist-info/WHEEL
arcface-0.0.8.dist-info/top_level.txt
arcface-0.0.8.dist-info/RECORD
