Metadata-Version: 2.1
Name: arcface
Version: 0.0.8
Summary: ArcFace face recognition implementation in Tensorflow Lite.
Home-page: https://github.com/mobilesec/arcface-tensorflowlite
Author: Philipp Hofer
Author-email: philipp.hofer@ins.jku.at
License: European Union Public Licence 1.2 (EUPL 1.2)
Platform: UNKNOWN
Classifier: License :: OSI Approved :: European Union Public Licence 1.2 (EUPL 1.2)
Classifier: Programming Language :: Python :: 3
Classifier: Operating System :: OS Independent
Requires-Dist: tensorflow (>=2.3.0)
Requires-Dist: pyyaml (>=5.3)
Requires-Dist: opencv-python (>=4.4)
Requires-Dist: numpy
Requires-Dist: requests (>=2.24.0)
Provides-Extra: default_model
Requires-Dist: astropy ; extra == 'default_model'
Provides-Extra: testing
Requires-Dist: pytest-runner ; extra == 'testing'
Requires-Dist: pytest ; extra == 'testing'
